[
  {
    "X": -108.84146,
    "Y": -267.85714,
    "Count": 8,
    "Type": "Parking"
  },
  {
    "X": -275,
    "Y": -643.4001,
    "Count": 4,
    "Type": "Parking"
  },
  {
    "X": -275,
    "Y": -667.53137,
    "Count": 4,
    "Type": "Parking"
  },
  {
    "X": -326.82927,
    "Y": -644.9083,
    "Count": 2,
    "Type": "Parking"
  },
  {
    "X": -185.06098,
    "Y": -690.15444,
    "Count": 4,
    "Type": "Parking"
  },
  {
    "X": -198.78049,
    "Y": -714.28571,
    "Count": 4,
    "Type": "Parking"
  },
  {
    "X": -125.60976,
    "Y": -729.36776,
    "Count": 2,
    "Type": "Parking"
  },
  {
    "X": -134.7561,
    "Y": -747.46622,
    "Count": 4,
    "Type": "Parking"
  },
  {
    "X": -85.97561,
    "Y": -712.77751,
    "Count": 10,
    "Type": "Parking"
  },
  {
    "X": -140.85366,
    "Y": 949.264,
    "Count": 1,
    "Type": "Electricity"
  },
  {
    "X": -1058.53659,
    "Y": -666.02317,
    "Count": 1,
    "Type": "Electricity"
  },
  {
    "X": -1122.56098,
    "Y": -702.22008,
    "Count": 1,
    "Type": "Electricity"
  },
  {
    "X": -1457.92683,
    "Y": -240.70946,
    "Count": 1,
    "Type": "Electricity"
  },
  {
    "X": -773.47561,
    "Y": -254.2833,
    "Count": 1,
    "Type": "Electricity"
  },
  {
    "X": -261.28049,
    "Y": -258.80792,
    "Count": 1,
    "Type": "Electricity"
  },
  {
    "X": -265.85366,
    "Y": -400.57915,
    "Count": 1,
    "Type": "Electricity"
  },
  {
    "X": -971.64634,
    "Y": -340.25097,
    "Count": 2,
    "Type": "Container"
  },
  {
    "X": -1076.82927,
    "Y": -334.21815,
    "Count": 3,
    "Type": "Container"
  },
  {
    "X": -1060.06098,
    "Y": -580.0555,
    "Count": 5,
    "Type": "Container"
  },
  {
    "X": -982.31707,
    "Y": -581.56371,
    "Count": 5,
    "Type": "Container"
  },
  {
    "X": -1148.47561,
    "Y": -691.66264,
    "Count": 3,
    "Type": "Container"
  },
  {
    "X": -1182.0122,
    "Y": -699.20367,
    "Count": 1,
    "Type": "Container"
  },
  {
    "X": -1151.52439,
    "Y": -616.25241,
    "Count": 2,
    "Type": "Container"
  },
  {
    "X": -1238.41463,
    "Y": -617.76062,
    "Count": 2,
    "Type": "Container"
  },
  {
    "X": -956.40244,
    "Y": -646.41651,
    "Count": 1,
    "Type": "Container"
  },
  {
    "X": -974.69512,
    "Y": -640.38369,
    "Count": 1,
    "Type": "Container"
  },
  {
    "X": -906.09756,
    "Y": -670.54778,
    "Count": 4,
    "Type": "Container"
  },
  {
    "X": -906.09756,
    "Y": -554.41602,
    "Count": 2,
    "Type": "Container"
  },
  {
    "X": -857.31707,
    "Y": -552.90782,
    "Count": 1,
    "Type": "Container"
  },
  {
    "X": -828.35366,
    "Y": -537.82577,
    "Count": 2,
    "Type": "Container"
  },
  {
    "X": -797.86585,
    "Y": -567.98986,
    "Count": 1,
    "Type": "Container"
  },
  {
    "X": -758.23171,
    "Y": -569.49807,
    "Count": 4,
    "Type": "Container"
  },
  {
    "X": -709.45122,
    "Y": -542.35039,
    "Count": 4,
    "Type": "Container"
  },
  {
    "X": -726.21951,
    "Y": -675.07239,
    "Count": 2,
    "Type": "Container"
  },
  {
    "X": -1561.58537,
    "Y": -287.4638,
    "Count": 4,
    "Type": "Container"
  },
  {
    "X": -1335.97561,
    "Y": 495.2944,
    "Count": 1,
    "Type": "Container"
  },
  {
    "X": -1296.34146,
    "Y": 469.65492,
    "Count": 2,
    "Type": "Container"
  },
  {
    "X": -779.57317,
    "Y": -269.36535,
    "Count": 2,
    "Type": "Container"
  },
  {
    "X": -645.42683,
    "Y": -340.25097,
    "Count": 1,
    "Type": "Container"
  },
  {
    "X": -217.07317,
    "Y": -239.20125,
    "Count": 3,
    "Type": "Container"
  },
  {
    "X": -41.76829,
    "Y": -151.72539,
    "Count": 3,
    "Type": "Container"
  },
  {
    "X": -81.40244,
    "Y": -257.29971,
    "Count": 1,
    "Type": "Container"
  },
  {
    "Type": "Container",
    "X": -691.1585365853653,
    "Y": 247.94884169884185,
    "Count": 1
  },
  {
    "Type": "Container",
    "X": -668.2926829268287,
    "Y": 260.0144787644789,
    "Count": 1
  },
  {
    "Type": "Parking",
    "X": -137.80487804877993,
    "Y": -791.2041505791505,
    "Count": 1
  },
  {
    "Type": "ATM",
    "X": -183.53658536585309,
    "Y": -845.4995173745173,
    "Count": 1
  },
  {
    "Type": "Parking",
    "X": -212.49999999999943,
    "Y": -807.7944015444015,
    "Count": 1
  },
  {
    "Type": "Parking",
    "X": -177.43902439024333,
    "Y": -902.8112934362933,
    "Count": 1
  },
  {
    "Type": "Container",
    "X": -191.15853658536528,
    "Y": -948.0574324324324,
    "Count": 1
  },
  {
    "Type": "ATM",
    "X": -335.975609756097,
    "Y": -1178.8127413127413,
    "Count": 1
  },
  {
    "Type": "Electricity",
    "X": -288.7195121951214,
    "Y": -1204.45222007722,
    "Count": 1
  },
  {
    "Type": "Container",
    "X": -276.52439024390185,
    "Y": -1234.6163127413126,
    "Count": 1
  },
  {
    "Type": "Container",
    "X": -288.7195121951214,
    "Y": -1266.28861003861,
    "Count": 1
  },
  {
    "Type": "Container",
    "X": -288.7195121951214,
    "Y": -1279.8624517374517,
    "Count": 1
  },
  {
    "Type": "Electricity",
    "X": -284.14634146341405,
    "Y": -1303.9937258687257,
    "Count": 1
  },
  {
    "Type": "Container",
    "X": -220.12195121951163,
    "Y": -1322.0921814671815,
    "Count": 1
  },
  {
    "Type": "Electricity",
    "X": -182.01219512195067,
    "Y": -1287.403474903475,
    "Count": 1
  },
  {
    "Type": "Electricity",
    "X": -79.87804878048725,
    "Y": -1210.4850386100386,
    "Count": 1
  },
  {
    "Type": "Electricity",
    "X": -104.26829268292627,
    "Y": -1162.2224903474903,
    "Count": 1
  },
  {
    "Type": "Electricity",
    "X": -140.85365853658482,
    "Y": -1153.1732625482625,
    "Count": 1
  },
  {
    "Type": "Electricity",
    "X": -160.67073170731652,
    "Y": -1086.8122586872587,
    "Count": 1
  },
  {
    "Type": "Container",
    "X": 14.63414634146397,
    "Y": -356.8412162162161,
    "Count": 1
  },
  {
    "Type": "Parking",
    "X": -12.804878048779933,
    "Y": -310.08687258687246,
    "Count": 1
  },
  {
    "Type": "Parking",
    "X": -64.63414634146285,
    "Y": -153.2335907335906,
    "Count": 1
  },
  {
    "Type": "Parking",
    "X": -148.475609756097,
    "Y": 11.160714285714423,
    "Count": 1
  },
  {
    "Type": "Container",
    "X": -90.54878048780432,
    "Y": -12.970559845559709,
    "Count": 1
  },
  {
    "Type": "Parking",
    "X": -197.25609756097504,
    "Y": 205.7191119691121,
    "Count": 1
  },
  {
    "Type": "Parking",
    "X": -236.89024390243847,
    "Y": 317.32625482625497,
    "Count": 1
  },
  {
    "Type": "Electricity",
    "X": -116.46341463414578,
    "Y": 347.49034749034763,
    "Count": 1
  },
  {
    "Type": "Container",
    "X": -66.1585365853653,
    "Y": 471.1631274131276,
    "Count": 1
  },
  {
    "Type": "Electricity",
    "X": -29.57317073170676,
    "Y": 492.27799227799244,
    "Count": 1
  },
  {
    "Type": "Container",
    "X": 5.487804878049335,
    "Y": 465.13030888030903,
    "Count": 1
  },
  {
    "Type": "Electricity",
    "X": -12.804878048779933,
    "Y": 460.60569498069515,
    "Count": 1
  },
  {
    "Type": "Container",
    "X": 64.93902439024446,
    "Y": 631.0328185328187,
    "Count": 1
  },
  {
    "Type": "Container",
    "X": 75.60975609756153,
    "Y": 611.4261583011585,
    "Count": 1
  },
  {
    "Type": "Container",
    "X": 83.23170731707373,
    "Y": 576.7374517374519,
    "Count": 1
  },
  {
    "Type": "Electricity",
    "X": -456.40243902438965,
    "Y": -631.3344594594594,
    "Count": 1
  },
  {
    "Type": "ATM",
    "X": -706.4024390243897,
    "Y": -604.186776061776,
    "Count": 1
  },
  {
    "Type": "Parking",
    "X": -808.536585365853,
    "Y": -1129.0419884169883,
    "Count": 1
  },
  {
    "Type": "Parking",
    "X": -863.4146341463409,
    "Y": -1201.4358108108108,
    "Count": 1
  },
  {
    "Type": "Container",
    "X": -866.4634146341458,
    "Y": -1243.6655405405404,
    "Count": 1
  },
  {
    "Type": "Container",
    "X": -845.1219512195116,
    "Y": -1257.2393822393822,
    "Count": 1
  },
  {
    "Type": "Container",
    "X": -835.975609756097,
    "Y": -1266.28861003861,
    "Count": 1
  },
  {
    "Type": "Container",
    "X": -832.9268292682921,
    "Y": -1264.7804054054054,
    "Count": 1
  },
  {
    "Type": "Container",
    "X": -826.8292682926823,
    "Y": -1263.2722007722007,
    "Count": 1
  },
  {
    "Type": "Container",
    "X": -831.4024390243897,
    "Y": -1234.6163127413126,
    "Count": 1
  },
  {
    "Type": "Container",
    "X": -837.4999999999994,
    "Y": -1234.6163127413126,
    "Count": 1
  },
  {
    "Type": "Container",
    "X": -831.4024390243897,
    "Y": -1243.6655405405404,
    "Count": 1
  },
  {
    "Type": "Container",
    "X": -811.585365853658,
    "Y": -1255.7311776061777,
    "Count": 1
  },
  {
    "Type": "Container",
    "X": -810.0609756097555,
    "Y": -1254.222972972973,
    "Count": 1
  },
  {
    "Type": "Container",
    "X": -787.1951219512189,
    "Y": -1278.354247104247,
    "Count": 1
  },
  {
    "Type": "Container",
    "X": -811.585365853658,
    "Y": -1279.8624517374517,
    "Count": 1
  },
  {
    "Type": "Container",
    "X": -817.6829268292677,
    "Y": -1273.8296332046332,
    "Count": 1
  },
  {
    "Type": "Container",
    "X": -781.0975609756092,
    "Y": -1299.469111969112,
    "Count": 1
  },
  {
    "Type": "Container",
    "X": -787.1951219512189,
    "Y": -1299.469111969112,
    "Count": 1
  },
  {
    "Type": "Container",
    "X": -773.475609756097,
    "Y": -1314.5511583011582,
    "Count": 1
  },
  {
    "Type": "Container",
    "X": -742.9878048780482,
    "Y": -1322.0921814671815,
    "Count": 1
  },
  {
    "Type": "Container",
    "X": -675.9146341463409,
    "Y": -1344.715250965251,
    "Count": 1
  },
  {
    "Type": "Container",
    "X": -646.9512195121945,
    "Y": -1350.7480694980695,
    "Count": 1
  },
  {
    "Type": "Container",
    "X": -662.1951219512189,
    "Y": -1371.8629343629343,
    "Count": 1
  },
  {
    "Type": "Container",
    "X": -639.3292682926824,
    "Y": -1380.912162162162,
    "Count": 1
  },
  {
    "Type": "Container",
    "X": -660.6707317073165,
    "Y": -1389.9613899613898,
    "Count": 1
  },
  {
    "Type": "Container",
    "X": -651.5243902439018,
    "Y": -1389.9613899613898,
    "Count": 1
  },
  {
    "Type": "Container",
    "X": -688.1097560975604,
    "Y": -1432.1911196911196,
    "Count": 1
  },
  {
    "Type": "Container",
    "X": -675.9146341463409,
    "Y": -1409.56805019305,
    "Count": 1
  },
  {
    "Type": "ATM",
    "X": -872.5609756097555,
    "Y": -181.88947876447864,
    "Count": 1
  },
  {
    "Type": "Electricity",
    "X": -874.0853658536579,
    "Y": -198.4797297297296,
    "Count": 1
  },
  {
    "Type": "ATM",
    "X": -720.1219512195116,
    "Y": -237.69305019305006,
    "Count": 1
  },
  {
    "Type": "ATM",
    "X": -692.6829268292677,
    "Y": -239.2012548262547,
    "Count": 1
  },
  {
    "Type": "Electricity",
    "X": -646.9512195121945,
    "Y": -317.62789575289565,
    "Count": 1
  },
  {
    "Type": "ATM",
    "X": -416.76829268292624,
    "Y": -699.2036679536678,
    "Count": 1
  },
  {
    "Type": "Container",
    "X": -433.5365853658531,
    "Y": -696.1872586872586,
    "Count": 1
  },
  {
    "Type": "Container",
    "X": -412.19512195121894,
    "Y": -738.4169884169884,
    "Count": 1
  },
  {
    "Type": "Parking",
    "X": -467.07317073170674,
    "Y": -908.8441119691119,
    "Count": 1
  },
  {
    "Type": "Electricity",
    "X": -334.45121951219454,
    "Y": -928.4507722007721,
    "Count": 1
  },
  {
    "Type": "Electricity",
    "X": -307.01219512195064,
    "Y": -883.2046332046331,
    "Count": 1
  },
  {
    "Type": "Electricity",
    "X": -303.96341463414575,
    "Y": -919.4015444015444,
    "Count": 1
  },
  {
    "Type": "Electricity",
    "X": -239.93902439024333,
    "Y": -1000.8445945945945,
    "Count": 1
  },
  {
    "Type": "Electricity",
    "X": -415.2439024390238,
    "Y": -1409.56805019305,
    "Count": 1
  },
  {
    "Type": "Parking",
    "X": -403.0487804878043,
    "Y": -1392.977799227799,
    "Count": 1
  },
  {
    "Type": "Parking",
    "X": -418.2926829268287,
    "Y": -1484.9782818532817,
    "Count": 1
  },
  {
    "Type": "Parking",
    "X": -381.70731707317015,
    "Y": -1489.5028957528957,
    "Count": 1
  },
  {
    "Type": "Parking",
    "X": -386.28048780487745,
    "Y": -1555.8638996138995,
    "Count": 1
  },
  {
    "Type": "Parking",
    "X": -649.9999999999994,
    "Y": -1584.5197876447876,
    "Count": 1
  },
  {
    "Type": "Electricity",
    "X": -685.0609756097555,
    "Y": -1542.2900579150578,
    "Count": 1
  },
  {
    "Type": "Electricity",
    "X": -704.8780487804872,
    "Y": -1519.6669884169883,
    "Count": 1
  },
  {
    "Type": "Parking",
    "X": -724.6951219512189,
    "Y": -1484.9782818532817,
    "Count": 1
  },
  {
    "Type": "Electricity",
    "X": -741.4634146341458,
    "Y": -1466.8798262548262,
    "Count": 1
  },
  {
    "Type": "Electricity",
    "X": -720.1219512195116,
    "Y": -1444.2567567567567,
    "Count": 1
  },
  {
    "Type": "Electricity",
    "X": -76.82926829268237,
    "Y": -1307.010135135135,
    "Count": 1
  },
  {
    "Type": "Electricity",
    "X": -49.39024390243847,
    "Y": -1346.2234555984555,
    "Count": 1
  },
  {
    "Type": "Electricity",
    "X": -73.7804878048775,
    "Y": -1257.2393822393822,
    "Count": 1
  }
]